{"stats":{"minecraft:custom":{"minecraft:time_since_rest":429,"minecraft:sprint_one_cm":105792,"minecraft:crouch_one_cm":857,"minecraft:play_time":15517,"minecraft:damage_taken":1024,"minecraft:deaths":4,"minecraft:walk_one_cm":48452,"minecraft:sneak_time":404,"minecraft:jump":343,"minecraft:damage_dealt":118,"minecraft:leave_game":1,"minecraft:walk_on_water_one_cm":89,"minecraft:time_since_death":580,"minecraft:total_world_time":15517,"minecraft:fall_one_cm":11871,"minecraft:fly_one_cm":73879,"minecraft:player_kills":1},"minecraft:used":{"minecraft:dirt":2,"minecraft:sand":3,"iceandfire:dragon_skull_ice":1,"tombstone:gift":2,"alexsmobs:animal_dictionary":1},"minecraft:picked_up":{"iceandfire:dragon_skull_ice":2,"iceandfire:dragonbone":1,"minecraft:sand":3,"minecraft:dirt":4},"minecraft:mined":{"minecraft:grass_block":1,"minecraft:sand":3,"minecraft:dirt":2},"minecraft:killed_by":{"minecraft:player":1,"undead_revamp2:the_moonflower":1}},"DataVersion":3465}